{
    "imgHeight": 1024, 
    "imgWidth": 2048, 
    "objects": [
        {
            "label": "cargroup", 
            "polygon": [
                [
                    2062, 
                    672
                ], 
                [
                    1935, 
                    660
                ], 
                [
                    1867, 
                    634
                ], 
                [
                    1825, 
                    643
                ], 
                [
                    1572, 
                    622
                ], 
                [
                    1576, 
                    546
                ], 
                [
                    1563, 
                    512
                ], 
                [
                    1509, 
                    512
                ], 
                [
                    1428, 
                    533
                ], 
                [
                    1395, 
                    504
                ], 
                [
                    1357, 
                    508
                ], 
                [
                    1352, 
                    457
                ], 
                [
                    1390, 
                    449
                ], 
                [
                    1677, 
                    453
                ], 
                [
                    1699, 
                    466
                ], 
                [
                    1737, 
                    440
                ], 
                [
                    1876, 
                    440
                ], 
                [
                    1910, 
                    453
                ], 
                [
                    1986, 
                    432
                ], 
                [
                    2049, 
                    440
                ], 
                [
                    2062, 
                    672
                ]
            ]
        }, 
        {
            "label": "car", 
            "polygon": [
                [
                    402, 
                    618
                ], 
                [
                    343, 
                    546
                ], 
                [
                    347, 
                    550
                ], 
                [
                    301, 
                    677
                ], 
                [
                    69, 
                    761
                ], 
                [
                    22, 
                    672
                ], 
                [
                    14, 
                    668
                ], 
                [
                    14, 
                    368
                ], 
                [
                    174, 
                    360
                ], 
                [
                    331, 
                    402
                ], 
                [
                    369, 
                    478
                ]
            ]
        }, 
        {
            "label": "cargroup", 
            "polygon": [
                [
                    807, 
                    516
                ], 
                [
                    759, 
                    531
                ], 
                [
                    733, 
                    525
                ], 
                [
                    730, 
                    554
                ], 
                [
                    603, 
                    582
                ], 
                [
                    623, 
                    421
                ], 
                [
                    637, 
                    378
                ], 
                [
                    707, 
                    388
                ], 
                [
                    729, 
                    410
                ], 
                [
                    788, 
                    416
                ], 
                [
                    808, 
                    471
                ], 
                [
                    812, 
                    495
                ]
            ]
        }, 
        {
            "label": "cargroup", 
            "polygon": [
                [
                    943, 
                    496
                ], 
                [
                    877, 
                    493
                ], 
                [
                    876, 
                    454
                ], 
                [
                    939, 
                    432
                ], 
                [
                    1036, 
                    434
                ], 
                [
                    1054, 
                    456
                ], 
                [
                    1055, 
                    495
                ], 
                [
                    997, 
                    499
                ]
            ]
        }, 
        {
            "label": "traffic sign", 
            "polygon": [
                [
                    1641, 
                    348
                ], 
                [
                    1659, 
                    348
                ], 
                [
                    1660, 
                    313
                ], 
                [
                    1641, 
                    314
                ], 
                [
                    1641, 
                    348
                ]
            ]
        }, 
        {
            "label": "road", 
            "polygon": [
                [
                    0, 
                    1014
                ], 
                [
                    919, 
                    529
                ], 
                [
                    1052, 
                    527
                ], 
                [
                    1135, 
                    509
                ], 
                [
                    1298, 
                    509
                ], 
                [
                    1314, 
                    539
                ], 
                [
                    1359, 
                    567
                ], 
                [
                    1475, 
                    608
                ], 
                [
                    1564, 
                    654
                ], 
                [
                    1602, 
                    683
                ], 
                [
                    1627, 
                    686
                ], 
                [
                    1762, 
                    708
                ], 
                [
                    1917, 
                    772
                ], 
                [
                    1975, 
                    773
                ], 
                [
                    1992, 
                    791
                ], 
                [
                    2042, 
                    1012
                ], 
                [
                    0, 
                    1014
                ]
            ]
        }, 
        {
            "label": "building", 
            "polygon": [
                [
                    11, 
                    16
                ], 
                [
                    9, 
                    275
                ], 
                [
                    73, 
                    287
                ], 
                [
                    86, 
                    83
                ], 
                [
                    122, 
                    86
                ], 
                [
                    122, 
                    278
                ], 
                [
                    228, 
                    300
                ], 
                [
                    364, 
                    371
                ], 
                [
                    473, 
                    7
                ], 
                [
                    11, 
                    16
                ]
            ]
        }, 
        {
            "label": "building", 
            "polygon": [
                [
                    1332, 
                    349
                ], 
                [
                    1326, 
                    242
                ], 
                [
                    1364, 
                    202
                ], 
                [
                    1460, 
                    179
                ], 
                [
                    1498, 
                    166
                ], 
                [
                    1548, 
                    103
                ], 
                [
                    1639, 
                    61
                ], 
                [
                    1617, 
                    340
                ], 
                [
                    1494, 
                    360
                ], 
                [
                    1397, 
                    374
                ]
            ]
        }, 
        {
            "label": "building", 
            "polygon": [
                [
                    1798, 
                    338
                ], 
                [
                    1762, 
                    56
                ], 
                [
                    1874, 
                    47
                ], 
                [
                    1896, 
                    25
                ], 
                [
                    1983, 
                    14
                ], 
                [
                    2017, 
                    25
                ], 
                [
                    2023, 
                    96
                ], 
                [
                    2012, 
                    349
                ], 
                [
                    1798, 
                    338
                ]
            ]
        }, 
        {
            "label": "pole", 
            "polygon": [
                [
                    686, 
                    364
                ], 
                [
                    689, 
                    247
                ], 
                [
                    695, 
                    247
                ], 
                [
                    692, 
                    364
                ], 
                [
                    686, 
                    364
                ]
            ]
        }, 
        {
            "label": "pole", 
            "polygon": [
                [
                    1648, 
                    417
                ], 
                [
                    1650, 
                    352
                ], 
                [
                    1656, 
                    352
                ], 
                [
                    1654, 
                    417
                ], 
                [
                    1648, 
                    417
                ]
            ]
        }, 
        {
            "label": "pole", 
            "polygon": [
                [
                    1649, 
                    304
                ], 
                [
                    1654, 
                    183
                ], 
                [
                    1660, 
                    183
                ], 
                [
                    1655, 
                    304
                ], 
                [
                    1649, 
                    304
                ]
            ]
        }, 
        {
            "label": "vegetation", 
            "polygon": [
                [
                    988, 
                    200
                ], 
                [
                    994, 
                    167
                ], 
                [
                    1025, 
                    92
                ], 
                [
                    1141, 
                    62
                ], 
                [
                    1256, 
                    66
                ], 
                [
                    1282, 
                    62
                ], 
                [
                    1336, 
                    14
                ], 
                [
                    1353, 
                    9
                ], 
                [
                    1465, 
                    2
                ], 
                [
                    1473, 
                    20
                ], 
                [
                    1471, 
                    45
                ], 
                [
                    1442, 
                    107
                ], 
                [
                    1426, 
                    113
                ], 
                [
                    1352, 
                    121
                ], 
                [
                    1308, 
                    103
                ], 
                [
                    1263, 
                    111
                ], 
                [
                    1257, 
                    118
                ], 
                [
                    1244, 
                    125
                ], 
                [
                    1238, 
                    193
                ], 
                [
                    1195, 
                    192
                ], 
                [
                    1193, 
                    196
                ], 
                [
                    1201, 
                    207
                ], 
                [
                    1246, 
                    222
                ], 
                [
                    1222, 
                    257
                ], 
                [
                    1201, 
                    269
                ], 
                [
                    1144, 
                    270
                ], 
                [
                    1127, 
                    261
                ], 
                [
                    1100, 
                    261
                ], 
                [
                    1068, 
                    251
                ], 
                [
                    1018, 
                    223
                ]
            ]
        }, 
        {
            "label": "building", 
            "polygon": [
                [
                    674, 
                    215
                ], 
                [
                    674, 
                    161
                ], 
                [
                    683, 
                    140
                ], 
                [
                    698, 
                    120
                ], 
                [
                    722, 
                    127
                ], 
                [
                    740, 
                    143
                ], 
                [
                    735, 
                    161
                ], 
                [
                    705, 
                    186
                ], 
                [
                    708, 
                    232
                ], 
                [
                    676, 
                    226
                ]
            ]
        }, 
        {
            "label": "pole", 
            "polygon": [
                [
                    99, 
                    99
                ], 
                [
                    109, 
                    101
                ], 
                [
                    102, 
                    316
                ], 
                [
                    97, 
                    317
                ], 
                [
                    92, 
                    312
                ]
            ]
        }, 
        {
            "label": "ego vehicle", 
            "polygon": [
                [
                    1732, 
                    1023
                ], 
                [
                    376, 
                    1023
                ], 
                [
                    418, 
                    1017
                ], 
                [
                    540, 
                    1002
                ], 
                [
                    814, 
                    978
                ], 
                [
                    1073, 
                    957
                ], 
                [
                    1169, 
                    952
                ], 
                [
                    1134, 
                    936
                ], 
                [
                    1122, 
                    905
                ], 
                [
                    1127, 
                    875
                ], 
                [
                    1146, 
                    857
                ], 
                [
                    1164, 
                    849
                ], 
                [
                    1191, 
                    848
                ], 
                [
                    1214, 
                    858
                ], 
                [
                    1230, 
                    881
                ], 
                [
                    1230, 
                    917
                ], 
                [
                    1216, 
                    937
                ], 
                [
                    1193, 
                    952
                ], 
                [
                    1369, 
                    961
                ], 
                [
                    1649, 
                    980
                ], 
                [
                    1920, 
                    1005
                ], 
                [
                    2047, 
                    1023
                ]
            ]
        }, 
        {
            "label": "out of roi", 
            "polygon": [
                [
                    0, 
                    0
                ], 
                [
                    2048, 
                    0
                ], 
                [
                    2048, 
                    1024
                ], 
                [
                    0, 
                    1024
                ], 
                [
                    0, 
                    0
                ], 
                [
                    5, 
                    5
                ], 
                [
                    5, 
                    1019
                ], 
                [
                    2043, 
                    1019
                ], 
                [
                    2043, 
                    5
                ], 
                [
                    5, 
                    5
                ]
            ]
        }
    ]
}